caspo/__init__.py
caspo/classify.py
caspo/control.py
caspo/design.py
caspo/learn.py
caspo/predict.py
caspo/visualize.py
caspo/console/__init__.py
caspo/console/handlers.py
caspo/console/main.py
caspo/core/__init__.py
caspo/core/clamping.py
caspo/core/clause.py
caspo/core/dataset.py
caspo/core/graph.py
caspo/core/hypergraph.py
caspo/core/literal.py
caspo/core/logicalnetwork.py
caspo/core/mapping.py
caspo/core/setup.py
caspo/data/ExtLiver/dataset.csv
caspo/data/ExtLiver/pkn.sif
caspo/data/ExtLiver/scenarios.csv
caspo/data/ExtLiver/setup.json
caspo/data/LiverDREAM/dataset.csv
caspo/data/LiverDREAM/pkn.sif
caspo/data/LiverDREAM/scenarios.csv
caspo/data/LiverDREAM/setup.json
caspo/data/LiverToy/dataset.csv
caspo/data/LiverToy/pkn.sif
caspo/data/LiverToy/scenarios.csv
caspo/data/LiverToy/setup.json
caspo/data/Toy/dataset.csv
caspo/data/Toy/pkn.sif
caspo/data/Toy/scenarios.csv
caspo/data/Toy/setup.json
caspo/encodings/classify/io.lp
caspo/encodings/control/encoding.lp
caspo/encodings/design/idesign.lp
caspo/encodings/learn/enumeration.lp
caspo/encodings/learn/fixpoint.lp
caspo/encodings/learn/guess.lp
caspo/encodings/learn/optimization.lp
caspo/encodings/learn/random.lp
caspo/encodings/learn/residual.lp
caspo-4.0.1.dist-info/LICENSE
caspo-4.0.1.dist-info/METADATA
caspo-4.0.1.dist-info/WHEEL
caspo-4.0.1.dist-info/entry_points.txt
caspo-4.0.1.dist-info/top_level.txt
caspo-4.0.1.dist-info/RECORD
