Metadata-Version: 2.1
Name: caspo
Version: 4.0.1
Summary: Reasoning on the response of logical signaling networks with Answer Set Programming
Home-page: http://bioasp.github.io/caspo/
Author: Santiago Videla
Author-email: santiago.videla@gmail.com
License: GPLv3+
Keywords: logical signaling networks systems biology answer set programming
Platform: UNKNOWN
Classifier: Intended Audience :: Science/Research
Classifier: Intended Audience :: Healthcare Industry
Classifier: License :: OSI Approved :: GNU General Public License v3 or later (GPLv3+)
Classifier: Operating System :: OS Independent
Classifier: Programming Language :: Python :: 2.7
Classifier: Topic :: Scientific/Engineering :: Artificial Intelligence
Classifier: Topic :: Scientific/Engineering :: Bio-Informatics
